canonicalwebteam/__init__.py
canonicalwebteam/templatefinder/__init__.py
canonicalwebteam/templatefinder/templatefinder.py
tests/__init__.py
tests/test_templatefinder.py
canonicalwebteam.templatefinder-1.0.0.dist-info/LICENSE.txt
canonicalwebteam.templatefinder-1.0.0.dist-info/METADATA
canonicalwebteam.templatefinder-1.0.0.dist-info/WHEEL
canonicalwebteam.templatefinder-1.0.0.dist-info/top_level.txt
canonicalwebteam.templatefinder-1.0.0.dist-info/RECORD
