Metadata-Version: 2.1
Name: canonicalwebteam.templatefinder
Version: 1.0.0
Summary: A module which attempts to load the corresponding templates directly from URLs, without the need to write a view for each URL.
Home-page: https://github.com/canonical-webteam/templatefinder
Author: Canonical Webteam
License: UNKNOWN
Platform: UNKNOWN
Requires-Dist: Flask (>=1.0)
Requires-Dist: mistune (==0.8.4)
Requires-Dist: python-frontmatter (>=0.4.5)
Requires-Dist: bleach (>=3.1)
